Pymagra/PyMaGra.py
Pymagra/__init__.py
Pymagra/__main__.py
Pymagra/pymagra_script.py
Pymagra/pymagra_start.py
Pymagra/data/__init__.py
Pymagra/data/data.py
Pymagra/data/geometrics.py
Pymagra/in_out/__init__.py
Pymagra/in_out/communication.py
Pymagra/in_out/dialog.py
Pymagra/in_out/earth.py
Pymagra/in_out/geometrics.py
Pymagra/in_out/io.py
Pymagra/inversion/__init__.py
Pymagra/inversion/inver.py
Pymagra/inversion/mag_grav_utilities.py
Pymagra/inversion/okabe.py
Pymagra/inversion/okabe_bak.py
Pymagra/inversion/potential_prism.py
Pymagra/plotting/Magnetics.ui
Pymagra/plotting/__init__.py
Pymagra/plotting/floating_plots.py
Pymagra/plotting/main_window.py
Pymagra/plotting/new_window.py
Pymagra/plotting/plotting.py
Pymagra/utilities/__init__.py
Pymagra/utilities/transforms.py
Pymagra/utilities/utilities.py
pymagra-25.6.2.dist-info/METADATA
pymagra-25.6.2.dist-info/WHEEL
pymagra-25.6.2.dist-info/entry_points.txt
pymagra-25.6.2.dist-info/top_level.txt
pymagra-25.6.2.dist-info/RECORD
