Metadata-Version: 2.4
Name: Pymagra
Version: 25.6.2
Summary: Data treatment for potential fields
Author-email: Hermann ZEYEN <hermann.zeyen@universite-paris-saclay.fr>
License: BSD-3-Clause
Classifier: Development Status :: 3 - Alpha
Classifier: Intended Audience :: Science/Research
Classifier: Intended Audience :: Developers
Classifier: Programming Language :: Python
Classifier: Programming Language :: Python :: 3
Classifier: Programming Language :: Python :: 3.10
Classifier: Programming Language :: Python :: 3.11
Classifier: Programming Language :: Python :: 3.12
Classifier: Topic :: Software Development
Classifier: Topic :: Scientific/Engineering
Classifier: Typing :: Typed
Classifier: Operating System :: Microsoft :: Windows
Classifier: Operating System :: POSIX
Classifier: Operating System :: Unix
Classifier: Operating System :: MacOS
Requires-Python: >=3.10
Requires-Dist: pathlib
Requires-Dist: datetime
Requires-Dist: scikit-learn
Requires-Dist: numpy
Requires-Dist: matplotlib
